{"cameraMode":{"drawMode":0,"name":"Shaded","section":"Shading Mode"},"sceneLighting":true,"audioPlay":false,"sceneViewState":{"showFog":true,"showMaterialUpdate":false,"showSkybox":true,"showFlares":true,"showImageEffects":true,"showParticleSystems":true},"in2DMode":false,"pivot":{"x":23.926815032958986,"y":1.610060214996338,"z":-7.297818183898926},"rotation":{"x":-0.05243375897407532,"y":-0.7259184718132019,"z":0.05194946378469467,"w":-0.6844520568847656},"size":3.5343754291534426,"orthographic":false}